[
    {
        "year": 2013,
        "months": [
            {
                "month": 10,
                "json": "json/bangumi-1310.json",
                "done": true
            }
        ]
    },
    {
        "year": 2014,
        "months": [
            {
                "month": 1,
                "json": "json/bangumi-1401.json",
                "done": true
            }, 
            {
                "month": 4,
                "json": "json/bangumi-1404.json",
                "done": true
            }, 
                {
                "month": 7,
                "json": "json/bangumi-1407.json",
                "done": true
            } 
        ]
    } 
]

